phuego/CLI.py
phuego/__init__.py
phuego/data/EGF_vs_Untreated_@min_15_63_240.txt
phuego/ego.py
phuego/ego2module.py
phuego/generate_net.py
phuego/load_seeds.py
phuego/network_rwr.py
phuego/phuego.py
phuego/phuego_mock.py
phuego/utils.py
phuego/utils_CLI.py
phuego-1.2.0.dist-info/LICENSE
phuego-1.2.0.dist-info/METADATA
phuego-1.2.0.dist-info/WHEEL
phuego-1.2.0.dist-info/entry_points.txt
phuego-1.2.0.dist-info/RECORD
