Metadata-Version: 2.1
Name: phuego
Version: 1.2.0
Summary: Propagation of phosphoproteomics signals
Home-page: https://github.com/haoqichen20/phuego
License: GPL-3.0-only
Keywords: Phosphoproteomics,network propagation
Author: Girolamo Giudice
Author-email: Girolamo.Giudice@gmail.com
Maintainer: Haoqi Chen
Maintainer-email: haoqichen20@gmail.com
Requires-Python: >=3.8,<3.13
Classifier: License :: OSI Approved :: GNU General Public License v3 (GPLv3)
Classifier: Programming Language :: Python :: 3
Classifier: Programming Language :: Python :: 3.8
Classifier: Programming Language :: Python :: 3.9
Classifier: Programming Language :: Python :: 3.10
Classifier: Programming Language :: Python :: 3.11
Requires-Dist: click (>=8.1.3)
Requires-Dist: igraph (>=0.10.2)
Requires-Dist: leidenalg (>=0.9.0)
Requires-Dist: numpy (>=1.24.3)
Requires-Dist: pandas (>=2.0.1)
Requires-Dist: requests (>2.29.0)
Requires-Dist: scikit-learn (>=1.2.2)
Requires-Dist: scipy (>=1.10.1)
Project-URL: Documentation, https://phuego.readthedocs.io/en/latest/index.html
Project-URL: Repository, https://github.com/haoqichen20/phuego
